bayesianroc/BayesianROC.py
bayesianroc/Test_Binary_Chance.py
bayesianroc/Test_Binary_Chance2.py
bayesianroc/__init__.py
bayesianroc/Helpers/BayesianROCFunctions.py
bayesianroc/Helpers/__init__.py
bayesianroc/Helpers/acLogging.py
bayesianroc/Helpers/bayesianAUC.py
bayesianroc/Helpers/pointMeasures.py
bayesianroc/Helpers/rocInputHelp.py
bayesianroc/Helpers/splitData.py
bayesianroc-0.0.9.dist-info/LICENSE
bayesianroc-0.0.9.dist-info/METADATA
bayesianroc-0.0.9.dist-info/WHEEL
bayesianroc-0.0.9.dist-info/top_level.txt
bayesianroc-0.0.9.dist-info/RECORD
