Metadata-Version: 2.1
Name: bayesianroc
Version: 0.0.9
Summary: Bayesian ROC analysis toolkit
Home-page: https://github.com/DR3AM-Hub/BayesianROC
Author: Andre Carrington
Author-email: amcarrin@gmail.com
Project-URL: Bug Tracker, https://github.com/DR3AM-Hub/BayesianROC/issues
Classifier: Programming Language :: Python :: 3
Classifier: License :: OSI Approved :: Apache Software License
Classifier: Operating System :: OS Independent
Requires-Python: >=3.6
License-File: LICENSE
